calculator_package/__init__.py
calculator_package/advanced_math_operation_module.py
calculator_package/math_operations_module.py
my_test_calculator_pkg-0.0.1.dist-info/METADATA
my_test_calculator_pkg-0.0.1.dist-info/WHEEL
my_test_calculator_pkg-0.0.1.dist-info/entry_points.txt
my_test_calculator_pkg-0.0.1.dist-info/top_level.txt
my_test_calculator_pkg-0.0.1.dist-info/RECORD
