Metadata-Version: 2.4
Name: my_test_calculator_pkg
Version: 0.0.1
Summary: A basic calculator package
Author: anil
Author-email: anilsai029@gmail.com
Classifier: Programming Language :: Python :: 3
Classifier: License :: OSI Approved :: MIT License
Classifier: Operating System :: OS Independent
Requires-Python: >=3.6
Dynamic: author
Dynamic: author-email
Dynamic: classifier
Dynamic: description
Dynamic: description-content-type
Dynamic: requires-python
Dynamic: summary
